Metadata-Version: 2.1
Name: verify-project-demo-51bfa141
Version: 0.1.1
Summary: A sample Python package that generates test code.
Home-page: https://github.com/yourusername/verify-project-demo-51bfa141
Author: doc
Author-email: nikoduck@gmail.com
Classifier: Programming Language :: Python :: 3
Classifier: License :: OSI Approved :: MIT License
Classifier: Operating System :: OS Independent
Requires-Python: >=3.6
License-File: LICENSE
